llm_venice/__init__.py
llm_venice/constants.py
llm_venice/utils.py
llm_venice/api/__init__.py
llm_venice/api/client.py
llm_venice/api/keys.py
llm_venice/api/refresh.py
llm_venice/api/upscale.py
llm_venice/cli/__init__.py
llm_venice/cli/api_keys.py
llm_venice/cli/characters.py
llm_venice/cli/command_hooks.py
llm_venice/cli/options.py
llm_venice/cli/upscale.py
llm_venice/cli/venice_group.py
llm_venice/models/__init__.py
llm_venice/models/chat.py
llm_venice/models/image.py
llm_venice-0.8.2.dist-info/licenses/LICENSE
llm_venice-0.8.2.dist-info/METADATA
llm_venice-0.8.2.dist-info/WHEEL
llm_venice-0.8.2.dist-info/entry_points.txt
llm_venice-0.8.2.dist-info/top_level.txt
llm_venice-0.8.2.dist-info/RECORD
