Metadata-Version: 2.4
Name: llm-venice
Version: 0.8.2
Summary: LLM plugin to access models available via the Venice API
Author: Arjan Mossel
License: Apache-2.0
Project-URL: Homepage, https://github.com/ar-jan/llm-venice
Project-URL: Changelog, https://github.com/ar-jan/llm-venice/releases
Project-URL: Issues, https://github.com/ar-jan/llm-venice/issues
Project-URL: CI, https://github.com/ar-jan/llm-venice/actions
Classifier: License :: OSI Approved :: Apache Software License
Requires-Python: >=3.10
License-File: LICENSE
Requires-Dist: llm>=0.27.1
Provides-Extra: test
Requires-Dist: jsonschema; extra == "test"
Requires-Dist: pytest; extra == "test"
Requires-Dist: pytest-httpx; extra == "test"
Requires-Dist: sqlite_utils; extra == "test"
Provides-Extra: dev
Requires-Dist: ruff>=0.14.8; extra == "dev"
Requires-Dist: ty>=0.0.1a32; extra == "dev"
Dynamic: license-file
